{
  "id": "skill:netlify-netlify-db",
  "slug": "netlify-netlify-db",
  "name": "netlify-db",
  "displayName": "netlify/netlify-db",
  "description": "Managed Postgres with deploy preview branching",
  "stars": 0,
  "category": "Official Skills by",
  "source": "voltagent",
  "url": "https://officialskills.sh/netlify/skills/netlify-db",
  "githubRepo": "",
  "readme": "# netlify/netlify-db\n\nManaged Postgres with deploy preview branching",
  "readmeHtml": "<h1>netlify/netlify-db</h1>\n<p>Managed Postgres with deploy preview branching</p>",
  "skillMd": "",
  "updatedAt": "2026-07-05T19:59:41.837Z",
  "author": {
    "login": "netlify",
    "name": "Netlify",
    "avatarUrl": "https://avatars.githubusercontent.com/u/7892489?v=4",
    "profileUrl": "https://github.com/netlify",
    "location": "San Francisco"
  },
  "location": {
    "id": "san-francisco",
    "label": "San Francisco, London, Austin, Lisbon, Singapore",
    "lat": 37.7749,
    "lon": -122.4194,
    "source": "github_profile"
  },
  "related": [
    {
      "slug": "netlify-netlify-functions",
      "displayName": "netlify/netlify-functions",
      "stars": 0,
      "relation": "source_overlap",
      "evidence": "author:netlify"
    },
    {
      "slug": "netlify-netlify-edge-functions",
      "displayName": "netlify/netlify-edge-functions",
      "stars": 0,
      "relation": "source_overlap",
      "evidence": "author:netlify"
    },
    {
      "slug": "netlify-netlify-blobs",
      "displayName": "netlify/netlify-blobs",
      "stars": 0,
      "relation": "source_overlap",
      "evidence": "author:netlify"
    },
    {
      "slug": "netlify-netlify-image-cdn",
      "displayName": "netlify/netlify-image-cdn",
      "stars": 0,
      "relation": "source_overlap",
      "evidence": "author:netlify"
    },
    {
      "slug": "netlify-netlify-forms",
      "displayName": "netlify/netlify-forms",
      "stars": 0,
      "relation": "source_overlap",
      "evidence": "author:netlify"
    },
    {
      "slug": "netlify-netlify-frameworks",
      "displayName": "netlify/netlify-frameworks",
      "stars": 0,
      "relation": "source_overlap",
      "evidence": "author:netlify"
    },
    {
      "slug": "netlify-netlify-caching",
      "displayName": "netlify/netlify-caching",
      "stars": 0,
      "relation": "source_overlap",
      "evidence": "author:netlify"
    },
    {
      "slug": "netlify-netlify-config",
      "displayName": "netlify/netlify-config",
      "stars": 0,
      "relation": "source_overlap",
      "evidence": "author:netlify"
    }
  ],
  "mapLocation": {
    "id": "san-francisco",
    "label": "San Francisco, London, Austin, Lisbon, Singapore",
    "lat": 37.7749,
    "lon": -122.4194,
    "source": "github_profile"
  }
}